yinhedata/YinHe.dll
yinhedata/__init__.py
yinhedata/_helpers.pyi
yinhedata/abc.py
yinhedata/base_protocol.py
yinhedata/client.py
yinhedata/client_exceptions.py
yinhedata/client_proto.py
yinhedata/client_reqrep.py
yinhedata/client_ws.py
yinhedata/compression_utils.py
yinhedata/connector.py
yinhedata/cookiejar.py
yinhedata/dat.dll
yinhedata/formdata.py
yinhedata/hdrs.py
yinhedata/helpers.py
yinhedata/http.py
yinhedata/http_exceptions.py
yinhedata/http_parser.py
yinhedata/http_websocket.py
yinhedata/http_writer.py
yinhedata/interface.dll
yinhedata/libcurl.py
yinhedata/librist.dll
yinhedata/log.py
yinhedata/mg_code.csv
yinhedata/multipart.py
yinhedata/payload.py
yinhedata/payload_streamer.py
yinhedata/py.typed
yinhedata/pytest_plugin.py
yinhedata/resolver.py
yinhedata/streams.py
yinhedata/syse.dll
yinhedata/tcp_helpers.py
yinhedata/test_utils.py
yinhedata/tracing.py
yinhedata/typedefs.py
yinhedata/w32-pthreads.dll
yinhedata/web.py
yinhedata/web_app.py
yinhedata/web_exceptions.py
yinhedata/web_fileresponse.py
yinhedata/web_log.py
yinhedata/web_middlewares.py
yinhedata/web_protocol.py
yinhedata/web_request.py
yinhedata/web_response.py
yinhedata/web_routedef.py
yinhedata/web_runner.py
yinhedata/web_server.py
yinhedata/web_urldispatcher.py
yinhedata/web_ws.py
yinhedata/worker.py
yinhedata/yinhe.py
yinhedata/igore/__init__.py
yinhedata/igore/httpssl.py
yinhedata/tj/__init__.py
yinhedata/tj/maths.py
yinhedata-1.3.31.dist-info/METADATA
yinhedata-1.3.31.dist-info/WHEEL
yinhedata-1.3.31.dist-info/top_level.txt
yinhedata-1.3.31.dist-info/RECORD
